{
  "Default": {
    "authLevel": 1,
    "AutoStart": "true",
    "Block clans kill reward": 1,
    "Block friends kill reward": 1,
    "ChatName": "EVENT",
    "Count": 2,
    "DisconnectPendingTimer": 30,
    "Display Distance": "true",
    "Excluded auth level": 1,
    "PauseeventTime": 30,
    "StarteventTime": 30
  },
  "IngameTime": {
    "End War Time": 8,
    "Start War Time": 18,
    "Use ingame timer": "false"
  },
  "Reward": {
    "KarmaSystem": {
      "PointToAdd": 1,
      "PointToRemove": 0
    },
    "Random": "true",
    "RewardFixing": "wood",
    "RewardFixingAmount": 10000
  }
}